downloader.py
main.py
soundcloud_processor.py
spotify_client.py
spotify_get-0.1.1.dist-info/METADATA
spotify_get-0.1.1.dist-info/WHEEL
spotify_get-0.1.1.dist-info/entry_points.txt
spotify_get-0.1.1.dist-info/top_level.txt
spotify_get-0.1.1.dist-info/RECORD
