Metadata-Version: 2.4
Name: spotify-get
Version: 0.1.1
Requires-Dist: spotipy
Requires-Dist: yt-dlp
Requires-Dist: python-dotenv
